collibra_assessments/__init__.py
collibra_assessments/api_client.py
collibra_assessments/configuration.py
collibra_assessments/rest.py
collibra_assessments/api/__init__.py
collibra_assessments/api/assessments_api.py
collibra_assessments/api/templates_api.py
collibra_assessments/models/__init__.py
collibra_assessments/models/answer.py
collibra_assessments/models/assessment.py
collibra_assessments/models/assessment_status.py
collibra_assessments/models/asset.py
collibra_assessments/models/asset_type.py
collibra_assessments/models/assets_answer.py
collibra_assessments/models/base_answer.py
collibra_assessments/models/base_asset.py
collibra_assessments/models/base_group.py
collibra_assessments/models/base_group_assignee.py
collibra_assessments/models/base_template.py
collibra_assessments/models/base_typed_user_or_group_assignee.py
collibra_assessments/models/base_user.py
collibra_assessments/models/base_user_assignee.py
collibra_assessments/models/base_user_or_group_assignee.py
collibra_assessments/models/boolean_answer.py
collibra_assessments/models/conduct_assessment_request.py
collibra_assessments/models/date_answer.py
collibra_assessments/models/group.py
collibra_assessments/models/group_assignee.py
collibra_assessments/models/item.py
collibra_assessments/models/items_answer.py
collibra_assessments/models/paged_assessments.py
collibra_assessments/models/paged_templates.py
collibra_assessments/models/question.py
collibra_assessments/models/question_and_answer.py
collibra_assessments/models/standard_error_response.py
collibra_assessments/models/template.py
collibra_assessments/models/text_answer.py
collibra_assessments/models/user.py
collibra_assessments/models/user_assignee.py
collibra_assessments/models/user_or_group_assignee.py
test/__init__.py
test/test_answer.py
test/test_assessment.py
test/test_assessment_status.py
test/test_assessments_api.py
test/test_asset.py
test/test_asset_type.py
test/test_assets_answer.py
test/test_base_answer.py
test/test_base_asset.py
collibra_assessments_100-1.0.0.dist-info/METADATA
collibra_assessments_100-1.0.0.dist-info/WHEEL
collibra_assessments_100-1.0.0.dist-info/top_level.txt
collibra_assessments_100-1.0.0.dist-info/RECORD
